watson/__init__.py
watson/filesystem/__init__.py
watson/filesystem/api.py
watson/filesystem/exceptions.py
watson/filesystem/backends/__init__.py
watson/filesystem/backends/abc.py
watson/filesystem/backends/local.py
watson/filesystem/backends/s3.py
watson_filesystem-2.0.0.dist-info/DESCRIPTION.rst
watson_filesystem-2.0.0.dist-info/METADATA
watson_filesystem-2.0.0.dist-info/RECORD
watson_filesystem-2.0.0.dist-info/WHEEL
watson_filesystem-2.0.0.dist-info/metadata.json
watson_filesystem-2.0.0.dist-info/top_level.txt
