Metadata-Version: 2.0
Name: watson-filesystem
Version: 2.0.0
Summary: Abstracted filesystems for Watson.
Home-page: http://github.com/bespohk/watson-filesystem
Author: Simon Coulton
Author-email: simon@bespohk.com
License: Copyright (c) 2012-2016 Bespohk, and is maintained by multiple
Requires-Dist: boto3
Requires-Dist: coverage
Requires-Dist: coveralls
Requires-Dist: pytest
Requires-Dist: pytest-cov
Provides-Extra: test
